{
  "datas": [
    {
      "id": "1",
      "data": "سیستم تعلیق",
      "imag": "https://upload.wikimedia.org/wikipedia/commons/thumb/4/41/Peugeot_508L_PHEV_001.jpg/280px-Peugeot_508L_PHEV_001.jpg",
      "title": "پلوس",
      "model": "Ford Mustang",
      "stars": 5,
      "order": 25,
      "price": 300000,
      "path": "پلوس"
    },
    {
      "id": "2",
      "data": "سیستم تعلیق",
      "imag": "https://upload.wikimedia.org/wikipedia/commons/thumb/1/17/Peugeot_605_red_vr.jpg/280px-Peugeot_605_red_vr.jpg",
      "title": "کیت تعلیق",
      "model": "Chevrolet Camaro",
      "stars": 4,
      "order": 70,
      "price": 250000,
      "path": "کیت تعلیق"
    }
  ]
}
